MANIFEST.in
README.rst
requirements-tests.txt
requirements.txt
setup.py
docs/Makefile
docs/application.rst
docs/conf.py
docs/conf.rst
docs/errors.rst
docs/hooks.rst
docs/index.rst
docs/request.rst
docs/resource.rst
docs/response.rst
docs/_static/.placeholder
docs/_templates/.placeholder
pyrs/__init__.py
pyrs/resource/__init__.py
pyrs/resource/base.py
pyrs/resource/conf.py
pyrs/resource/errors.py
pyrs/resource/hooks.py
pyrs/resource/lib.py
pyrs/resource/request.py
pyrs/resource/resource.py
pyrs/resource/response.py
pyrs/resource/tests/__init__.py
pyrs/resource/tests/test_base.py
pyrs/resource/tests/test_errors.py
pyrs/resource/tests/test_functionality.py
pyrs/resource/tests/test_request.py
pyrs/resource/tests/test_response.py
pyrs_resource.egg-info/PKG-INFO
pyrs_resource.egg-info/SOURCES.txt
pyrs_resource.egg-info/dependency_links.txt
pyrs_resource.egg-info/not-zip-safe
pyrs_resource.egg-info/pbr.json
pyrs_resource.egg-info/requires.txt
pyrs_resource.egg-info/top_level.txt